regressorpipeline/__init__.py
regressorpipeline/cnn_module.py
regressorpipeline/data_utils.py
regressorpipeline/models.py
regressorpipeline/predict.py
regressorpipeline/train.py
regressorpipeline/visualize.py
firecast_pipeline-0.1.5.dist-info/METADATA
firecast_pipeline-0.1.5.dist-info/WHEEL
firecast_pipeline-0.1.5.dist-info/entry_points.txt
firecast_pipeline-0.1.5.dist-info/top_level.txt
firecast_pipeline-0.1.5.dist-info/RECORD
