Metadata-Version: 2.1
Name: firecast_pipeline
Version: 0.1.5
Summary: Unified regression pipeline for fire risk prediction.
Author: Allan Zhang
Author-email: yaoyu.zhang@mail.utoronto.ca
Requires-Python: >=3.7
Requires-Dist: pandas
Requires-Dist: numpy
Requires-Dist: scikit-learn
Requires-Dist: statsmodels
Requires-Dist: xgboost
Requires-Dist: torch
Requires-Dist: optuna
Requires-Dist: openpyxl
Requires-Dist: joblib
Requires-Dist: plotly
